gd_diff.py
gns_deb_diff/__init__.py
gns_deb_diff/_version.py
gns_deb_diff/data/wiki-header.txt
gns_deb_diff-0.1.1.dist-info/DESCRIPTION.rst
gns_deb_diff-0.1.1.dist-info/METADATA
gns_deb_diff-0.1.1.dist-info/RECORD
gns_deb_diff-0.1.1.dist-info/WHEEL
gns_deb_diff-0.1.1.dist-info/entry_points.txt
gns_deb_diff-0.1.1.dist-info/metadata.json
gns_deb_diff-0.1.1.dist-info/top_level.txt
