Metadata-Version: 2.0
Name: gns-deb-diff
Version: 0.1.1
Summary: Documents difference between gNewsSense and Debian.
Home-page: https://git.ricketyspace.net/gns-deb-diff
Author: rsiddharth
Author-email: rsiddharth@ninthfloor.org
License: Public Domain
Keywords: gNewSense Debian documentation
Platform: UNKNOWN
Classifier: Development Status :: 2 - Pre-Alpha
Classifier: Environment :: Console
Classifier: Intended Audience :: Developers
Classifier: License :: CC0 1.0 Universal (CC0 1.0) Public Domain Dedication
Classifier: Operating System :: POSIX :: Linux
Classifier: Programming Language :: Python :: 3.5
Classifier: Programming Language :: Python :: 3 :: Only
Classifier: Topic :: Software Development :: Documentation
Classifier: Topic :: Text Processing :: General
Requires-Dist: beautifulsoup4
Requires-Dist: requests
